{
    "$schema": "https://developer.microsoft.com/json-schemas/rush/v5/rush.schema.json",
    "rushVersion": "5.26.0",
    "pnpmVersion": "5.2.2",
    "pnpmOptions": {
        "strictPeerDependencies": true,
        "resolutionStrategy": "fast"
    },
    "nodeSupportedVersionRange": "^12.13.0",
    "ensureConsistentVersions": true,
    "projectFolderMinDepth": 2,
    "projectFolderMaxDepth": 2,
    "approvedPackagesPolicy": {
        "reviewCategories": [
            "production"
        ],
        "ignoredNpmScopes": [
            "@types"
        ]
    },
    "gitPolicy": {
        "versionBumpCommitMessage": "Applying package updates. [skip-ci]"
    },
    "repository": {
        "url": "https://github.com/mpiroc-org/utils.git"
    },
    "eventHooks": {
        "preRushInstall": [],
        "postRushInstall": [],
        "preRushBuild": [],
        "postRushBuild": []
    },
    "variants": [],
    "projects": [
        {
            "packageName": "@mpiroc-org/iterable",
            "projectFolder": "packages/iterable",
            "reviewCategory": "production",
            "shouldPublish": true,
            "versionPolicyName": "default"
        },
        {
            "packageName": "@mpiroc-org/logging",
            "projectFolder": "packages/logging",
            "reviewCategory": "production",
            "shouldPublish": true,
            "versionPolicyName": "default"
        },
        {
            "packageName": "@mpiroc-org/promise",
            "projectFolder": "packages/promise",
            "reviewCategory": "production",
            "shouldPublish": true,
            "versionPolicyName": "default"
        }
    ]
}